{
    "data": [
        {
            "Id": 1,
            "Title": "57&FAL",
            "Author": "Idrikoseal",
            "ThumImg": "https://twcdn.imtxwy.com/tw/gf/illustration/js/cr001.jpg",
            "LargeImg": "https://twcdn.imtxwy.com/tw/gf/illustration/js/cr001-full.jpg"
        },
        {
            "Id": 2,
            "Title": "PKPKP",
            "Author": "沈昱廷",
            "ThumImg": "https://twcdn.imtxwy.com/tw/gf/illustration/js/cr002.jpg",
            "LargeImg": "https://twcdn.imtxwy.com/tw/gf/illustration/js/cr002-full.jpg"
        },
        {
            "Id": 3,
            "Title": "請幫Spectre M4加星",
            "Author": "泡麵+蛋",
            "ThumImg": "https://twcdn.imtxwy.com/tw/gf/illustration/js/cr003.jpg",
            "LargeImg": "https://twcdn.imtxwy.com/tw/gf/illustration/js/cr003-full.jpg"
        },
        {
            "Id": 4,
            "Title": "pkp＆g36",
            "Author": "張晧哲",
            "ThumImg": "https://twcdn.imtxwy.com/tw/gf/illustration/js/cr004.jpg",
            "LargeImg": "https://twcdn.imtxwy.com/tw/gf/illustration/js/cr004-full.jpg"
        },
        {
            "Id": 5,
            "Title": "永遠的404&一周年聖誕賀圖",
            "Author": "神楓御紫",
            "ThumImg": "https://twcdn.imtxwy.com/tw/gf/illustration/js/cr005.jpg",
            "LargeImg": "https://twcdn.imtxwy.com/tw/gf/illustration/js/cr005-full.jpg"
        },
        {
            "Id": 6,
            "Title": "愉快的交換禮物",
            "Author": "Idrikoseal",
            "ThumImg": "https://twcdn.imtxwy.com/tw/gf/illustration/js/cr006.jpg",
            "LargeImg": "https://twcdn.imtxwy.com/tw/gf/illustration/js/cr006-full.jpg"
        },
        {
            "Id": 7,
            "Title": "SVD誓約",
            "Author": "陳于軒",
            "ThumImg": "https://twcdn.imtxwy.com/tw/gf/illustration/js/cr007.jpg",
            "LargeImg": "https://twcdn.imtxwy.com/tw/gf/illustration/js/cr007-full.jpg"
        },
        {
            "Id": 8,
            "Title": "PPK",
            "Author": "雯子",
            "ThumImg": "https://twcdn.imtxwy.com/tw/gf/illustration/js/cr008.jpg",
            "LargeImg": "https://twcdn.imtxwy.com/tw/gf/illustration/js/cr008-full.jpg"
        },
        {
            "Id": 9,
            "Title": "M16A1的犧牲",
            "Author": "陳聖文",
            "ThumImg": "https://twcdn.imtxwy.com/tw/gf/illustration/js/cr009.jpg",
            "LargeImg": "https://twcdn.imtxwy.com/tw/gf/illustration/js/cr009-full.jpg"
        },
        {
            "Id": 10,
            "Title": "MG4與MG4",
            "Author": "搭碰",
            "ThumImg": "https://twcdn.imtxwy.com/tw/gf/illustration/js/cr010.jpg",
            "LargeImg": "https://twcdn.imtxwy.com/tw/gf/illustration/js/cr010-full.jpg"
        },
        {
            "Id": 11,
            "Title": "SV-98",
            "Author": "LianJin",
            "ThumImg": "https://twcdn.imtxwy.com/tw/gf/illustration/js/cr011.jpg",
            "LargeImg": "https://twcdn.imtxwy.com/tw/gf/illustration/js/cr011-full.jpg"
        },
        {
            "Id": 12,
            "Title": "AR15",
            "Author": "朱斯特",
            "ThumImg": "https://twcdn.imtxwy.com/tw/gf/illustration/js/cr013.jpg",
            "LargeImg": "https://twcdn.imtxwy.com/tw/gf/illustration/js/cr012-full.jpg"
        },
        {
            "Id": 13,
            "Title": "SR-3MP Candy cane rabbit",
            "Author": "EGa",
            "ThumImg": "https://twcdn.imtxwy.com/tw/gf/illustration/js/cr014.jpg",
            "LargeImg": "https://twcdn.imtxwy.com/tw/gf/illustration/js/cr013-full.jpg"
        },
        {
            "Id": 14,
            "Title": "沒有妳的地方...不算歸宿...",
            "Author": "陳聖文",
            "ThumImg": "https://twcdn.imtxwy.com/tw/gf/illustration/js/cr015.jpg",
            "LargeImg": "https://twcdn.imtxwy.com/tw/gf/illustration/js/cr014-full.jpg"
        },
        {
            "Id": 15,
            "Title": "姊姊在看什麼呢?",
            "Author": "ALONE",
            "ThumImg": "https://twcdn.imtxwy.com/tw/gf/illustration/js/cr016.jpg",
            "LargeImg": "https://twcdn.imtxwy.com/tw/gf/illustration/js/cr015-full.jpg"
        },
        {
            "Id": 16,
            "Title": "星空下的誓約",
            "Author": "愛麗絲",
            "ThumImg": "https://twcdn.imtxwy.com/tw/gf/illustration/js/cr017.jpg",
            "LargeImg": "https://twcdn.imtxwy.com/tw/gf/illustration/js/cr016-full.jpg"
        },
        {
            "Id": 17,
            "Title": "MG5",
            "Author": "蟲蟲",
            "ThumImg": "https://twcdn.imtxwy.com/tw/gf/illustration/js/cr018.jpg",
            "LargeImg": "https://twcdn.imtxwy.com/tw/gf/illustration/js/cr017-full.jpg"
        },
        {
            "Id": 18,
            "Title": "雪下赴約，喵?",
            "Author": "NAGI",
            "ThumImg": "https://twcdn.imtxwy.com/tw/gf/illustration/js/cr019.jpg",
            "LargeImg": "https://twcdn.imtxwy.com/tw/gf/illustration/js/cr018-full.jpg"
        },
        {
            "Id": 19,
            "Title": "404與直播",
            "Author": "戰備糧食",
            "ThumImg": "https://twcdn.imtxwy.com/tw/gf/illustration/js/cr020.jpg",
            "LargeImg": "https://twcdn.imtxwy.com/tw/gf/illustration/js/cr019-full.jpg"
        },
        {
            "Id": 20,
            "Title": "Flowers Of the Battlefield",
            "Author": "SATO",
            "ThumImg": "https://twcdn.imtxwy.com/tw/gf/illustration/js/cr021.jpg",
            "LargeImg": "https://twcdn.imtxwy.com/tw/gf/illustration/js/cr020-full.jpg"
        },
        {
            "Id": 21,
            "Title": "PSG-1",
            "Author": "ECHOLESS",
            "ThumImg": "https://twcdn.imtxwy.com/tw/gf/illustration/js/cr022.jpg",
            "LargeImg": "https://twcdn.imtxwy.com/tw/gf/illustration/js/cr021-full.jpg"
        },
        {
            "Id": 22,
            "Title": "初次見面 指揮官",
            "Author": "歐郎",
            "ThumImg": "https://twcdn.imtxwy.com/tw/gf/illustration/js/cr023.jpg",
            "LargeImg": "https://twcdn.imtxwy.com/tw/gf/illustration/js/cr022-full.jpg"
        },
        {
            "Id": 23,
            "Title": "我的隊伍(祈願)",
            "Author": "Anjisbai",
            "ThumImg": "https://twcdn.imtxwy.com/tw/gf/illustration/js/cr024.jpg",
            "LargeImg": "https://twcdn.imtxwy.com/tw/gf/illustration/js/cr023-full.jpg"
        },
        {
            "Id": 24,
            "Title": "締結誓約",
            "Author": "Aiban",
            "ThumImg": "https://twcdn.imtxwy.com/tw/gf/illustration/js/cr025.jpg",
            "LargeImg": "https://twcdn.imtxwy.com/tw/gf/illustration/js/cr024-full.jpg"
        },
        {
            "Id": 25,
            "Title": "IWS2000戰鬥出擊",
            "Author": "Yuriha",
            "ThumImg": "https://twcdn.imtxwy.com/tw/gf/illustration/js/cr026.jpg",
            "LargeImg": "https://twcdn.imtxwy.com/tw/gf/illustration/js/cr025-full.jpg"
        },
        {
            "Id": 26,
            "Title": "年末聚餐",
            "Author": "HsuBo",
            "ThumImg": "https://twcdn.imtxwy.com/tw/gf/illustration/js/cr027.jpg",
            "LargeImg": "https://twcdn.imtxwy.com/tw/gf/illustration/js/cr026-full.jpg"
        },
        {
            "Id": 27,
            "Title": "雪後晴天",
            "Author": "燉羊肉",
            "ThumImg": "https://twcdn.imtxwy.com/tw/gf/illustration/js/cr028.jpg",
            "LargeImg": "https://twcdn.imtxwy.com/tw/gf/illustration/js/cr027-full.jpg"
        },
        {
            "Id": 28,
            "Title": "The Dawn",
            "Author": "DriftKingTW",
            "ThumImg": "https://twcdn.imtxwy.com/tw/gf/illustration/js/cr029.jpg",
            "LargeImg": "https://twcdn.imtxwy.com/tw/gf/illustration/js/cr028-full.jpg"
        },
        {
            "Id": 29,
            "Title": "與Zas誓約的那一天",
            "Author": "奶凍",
            "ThumImg": "https://twcdn.imtxwy.com/tw/gf/illustration/js/cr030.jpg",
            "LargeImg": "https://twcdn.imtxwy.com/tw/gf/illustration/js/cr029-full.jpg"
        },
        {
            "Id": 30,
            "Title": "NZ的眼神殺",
            "Author": "OriKaza織風",
            "ThumImg": "https://twcdn.imtxwy.com/tw/gf/illustration/js/cr031.jpg",
            "LargeImg": "https://twcdn.imtxwy.com/tw/gf/illustration/js/cr030-full.jpg"
        },
        {
            "Id": 31,
            "Title": "少女前線-M9．Samurai Edge",
            "Author": "松茸 マツタケ",
            "ThumImg": "https://twcdn.imtxwy.com/tw/gf/illustration/js/cr032.jpg",
            "LargeImg": "https://twcdn.imtxwy.com/tw/gf/illustration/js/cr031-full.jpg"
        },
        {
            "Id": 32,
            "Title": "NN的德皇跟閃電需要鑽石",
            "Author": "NN",
            "ThumImg": "https://twcdn.imtxwy.com/tw/gf/illustration/js/cr033.jpg",
            "LargeImg": "https://twcdn.imtxwy.com/tw/gf/illustration/js/cr032-full.jpg"
        },
        {
            "Id": 33,
            "Title": "GMKV",
            "Author": "Mangoサ",
            "ThumImg": "https://twcdn.imtxwy.com/tw/gf/illustration/js/cr034.jpg",
            "LargeImg": "https://twcdn.imtxwy.com/tw/gf/illustration/js/cr033-full.jpg"
        },
        {
            "Id": 34,
            "Title": "Dream Heaven",
            "Author": "Akiya豆包",
            "ThumImg": "https://twcdn.imtxwy.com/tw/gf/illustration/js/cr035.jpg",
            "LargeImg": "https://twcdn.imtxwy.com/tw/gf/illustration/js/cr034-full.jpg"
        },
        {
            "Id": 35,
            "Title": "上司和下屬之間很難得到共識",
            "Author": "44444",
            "ThumImg": "https://twcdn.imtxwy.com/tw/gf/illustration/js/cr036.jpg",
            "LargeImg": "https://twcdn.imtxwy.com/tw/gf/illustration/js/cr035-full.jpg"
        },
        {
            "Id": 36,
            "Title": "SOP V.S. POI",
            "Author": "松茸 マツタケ",
            "ThumImg": "https://twcdn.imtxwy.com/tw/gf/illustration/js/cr037.jpg",
            "LargeImg": "https://twcdn.imtxwy.com/tw/gf/illustration/js/cr036-full.jpg"
        },
        {
            "Id": 37,
            "Title": "最重要的日子",
            "Author": "太雨",
            "ThumImg": "https://twcdn.imtxwy.com/tw/gf/illustration/js/cr038.jpg",
            "LargeImg": "https://twcdn.imtxwy.com/tw/gf/illustration/js/cr037-full.jpg"
        },
        {
            "Id": 38,
            "Title": "AFTER WAR TEA TIME － 戰後的下午茶",
            "Author": "RONI",
            "ThumImg": "https://twcdn.imtxwy.com/tw/gf/illustration/js/cr039.jpg",
            "LargeImg": "https://twcdn.imtxwy.com/tw/gf/illustration/js/cr038-full.jpg"
        },
        {
            "Id": 39,
            "Title": "鍋鍋沙與妖精們的點心時間",
            "Author": "菇菇窩",
            "ThumImg": "https://twcdn.imtxwy.com/tw/gf/illustration/js/cr040.jpg",
            "LargeImg": "https://twcdn.imtxwy.com/tw/gf/illustration/js/cr039-full.jpg"
        },
        {
            "Id": 40,
            "Title": "辣翅與遊戲與春天的雪妖精",
            "Author": "NiiE",
            "ThumImg": "https://twcdn.imtxwy.com/tw/gf/illustration/js/cr041.jpg",
            "LargeImg": "https://twcdn.imtxwy.com/tw/gf/illustration/js/cr040-full.jpg"
        },
        {
            "Id": 41,
            "Title": "溫徹斯特",
            "Author": "Leni",
            "ThumImg": "https://twcdn.imtxwy.com/tw/gf/illustration/js/cr042.jpg",
            "LargeImg": "https://twcdn.imtxwy.com/tw/gf/illustration/js/cr041-full.jpg"
        },
        {
            "Id": 42,
            "Title": "與少女們的聖誕節回憶",
            "Author": "温(Wen)",
            "ThumImg": "https://twcdn.imtxwy.com/tw/gf/illustration/js/cr043.jpg",
            "LargeImg": "https://twcdn.imtxwy.com/tw/gf/illustration/js/cr042-full.jpg"
        },
        {
            "Id": 43,
            "Title": "退場日常打工生活",
            "Author": "FatKE",
            "ThumImg": "https://twcdn.imtxwy.com/tw/gf/illustration/js/cr044.jpg",
            "LargeImg": "https://twcdn.imtxwy.com/tw/gf/illustration/js/cr043-full.jpg"
        },
        {
            "Id": 44,
            "Title": "MG4-等待救援",
            "Author": "Deepconvict",
            "ThumImg": "https://twcdn.imtxwy.com/tw/gf/illustration/js/cr045.jpg",
            "LargeImg": "https://twcdn.imtxwy.com/tw/gf/illustration/js/cr044-full.jpg"
        },
        {
            "Id": 45,
            "Title": "9A91好感度200",
            "Author": "傻阿貓",
            "ThumImg": "https://twcdn.imtxwy.com/tw/gf/illustration/js/cr046.jpg",
            "LargeImg": "https://twcdn.imtxwy.com/tw/gf/illustration/js/cr045-full.jpg"
        },
        {
            "Id": 46,
            "Title": "新年快樂",
            "Author": "Jinko_神子",
            "ThumImg": "https://twcdn.imtxwy.com/tw/gf/illustration/js/cr047.jpg",
            "LargeImg": "https://twcdn.imtxwy.com/tw/gf/illustration/js/cr046-full.jpg"
        },
        {
            "Id": 47,
            "Title": "賀喜一周年",
            "Author": "悅湧",
            "ThumImg": "https://twcdn.imtxwy.com/tw/gf/illustration/js/cr048.jpg",
            "LargeImg": "https://twcdn.imtxwy.com/tw/gf/illustration/js/cr047-full.jpg"
        },
        {
            "Id": 48,
            "Title": "拮据前線",
            "Author": "阿非",
            "ThumImg": "https://twcdn.imtxwy.com/tw/gf/illustration/js/cr049.jpg",
            "LargeImg": "https://twcdn.imtxwy.com/tw/gf/illustration/js/cr048-full.jpg"
        },
        {
            "Id": 49,
            "Title": "《狙擊》",
            "Author": "科科笑",
            "ThumImg": "https://twcdn.imtxwy.com/tw/gf/illustration/js/cr050.jpg",
            "LargeImg": "https://twcdn.imtxwy.com/tw/gf/illustration/js/cr049-full.jpg"
        },
        {
            "Id": 50,
            "Title": "memories",
            "Author": "貓屋",
            "ThumImg": "https://twcdn.imtxwy.com/tw/gf/illustration/js/cr051.jpg",
            "LargeImg": "https://twcdn.imtxwy.com/tw/gf/illustration/js/cr050-full.jpg"
        },
        {
            "Id": 51,
            "Title": "不觸發警報的專家",
            "Author": "Leaf98k",
            "ThumImg": "https://twcdn.imtxwy.com/tw/gf/illustration/js/cr052.jpg",
            "LargeImg": "https://twcdn.imtxwy.com/tw/gf/illustration/js/cr051-full.jpg"
        },
        {
            "Id": 52,
            "Title": "等..在哪裡啊?!",
            "Author": "HiIdka",
            "ThumImg": "https://twcdn.imtxwy.com/tw/gf/illustration/js/cr053.jpg",
            "LargeImg": "https://twcdn.imtxwy.com/tw/gf/illustration/js/cr052-full.jpg"
        },
        {
            "Id": 53,
            "Title": "來該跟我去吃辣雞囉!",
            "Author": "煉金",
            "ThumImg": "https://twcdn.imtxwy.com/tw/gf/illustration/js/cr054.jpg",
            "LargeImg": "https://twcdn.imtxwy.com/tw/gf/illustration/js/cr053-full.jpg"
        },
        {
            "Id": 54,
            "Title": "等待指揮官來迎接的一刻",
            "Author": "羅吉",
            "ThumImg": "https://twcdn.imtxwy.com/tw/gf/illustration/js/cr055.jpg",
            "LargeImg": "https://twcdn.imtxwy.com/tw/gf/illustration/js/cr054-full.jpg"
        },
        {
            "Id": 55,
            "Title": "夢想的侵略者",
            "Author": "羅吉",
            "ThumImg": "https://twcdn.imtxwy.com/tw/gf/illustration/js/cr056.jpg",
            "LargeImg": "https://twcdn.imtxwy.com/tw/gf/illustration/js/cr055-full.jpg"
        },
        {
            "Id": 56,
            "Title": "Zas M21誓約之日",
            "Author": "裂裂",
            "ThumImg": "https://twcdn.imtxwy.com/tw/gf/illustration/js/cr057.jpg",
            "LargeImg": "https://twcdn.imtxwy.com/tw/gf/illustration/js/cr056-full.jpg"
        },
        {
            "Id": 57,
            "Title": "往夢境出發！404小隊！",
            "Author": "Heion/海翁",
            "ThumImg": "https://twcdn.imtxwy.com/tw/gf/illustration/js/cr058.jpg",
            "LargeImg": "https://twcdn.imtxwy.com/tw/gf/illustration/js/cr057-full.jpg"
        },
        {
            "Id": 58,
            "Title": "鐵血少女們",
            "Author": "未永",
            "ThumImg": "https://twcdn.imtxwy.com/tw/gf/illustration/js/cr059.jpg",
            "LargeImg": "https://twcdn.imtxwy.com/tw/gf/illustration/js/cr058-full.jpg"
        },
        {
            "Id": 59,
            "Title": "散櫻落花春雨時",
            "Author": "Yoko/子7",
            "ThumImg": "https://twcdn.imtxwy.com/tw/gf/illustration/js/cr060.jpg",
            "LargeImg": "https://twcdn.imtxwy.com/tw/gf/illustration/js/cr059-full.jpg"
        },
        {
            "Id": 60,
            "Title": "三人日常",
            "Author": "手腫",
            "ThumImg": "https://twcdn.imtxwy.com/tw/gf/illustration/js/cr061.jpg",
            "LargeImg": "https://twcdn.imtxwy.com/tw/gf/illustration/js/cr060-full.jpg"
        },
        {
            "Id": 61,
            "Title": "一周年紀念",
            "Author": "Millo",
            "ThumImg": "https://twcdn.imtxwy.com/tw/gf/illustration/js/cr062.jpg",
            "LargeImg": "https://twcdn.imtxwy.com/tw/gf/illustration/js/cr061-full.jpg"
        },
        {
            "Id": 62,
            "Title": "G41 新年繪",
            "Author": "Gumifans",
            "ThumImg": "https://twcdn.imtxwy.com/tw/gf/illustration/js/cr063.jpg",
            "LargeImg": "https://twcdn.imtxwy.com/tw/gf/illustration/js/cr062-full.jpg"
        },
        {
            "Id": 63,
            "Title": "RFB&索米-我要成為偶像",
            "Author": "琟亞",
            "ThumImg": "https://twcdn.imtxwy.com/tw/gf/illustration/js/cr064.jpg",
            "LargeImg": "https://twcdn.imtxwy.com/tw/gf/illustration/js/cr063-full.jpg"
        },
        {
            "Id": 64,
            "Title": "真實的妳",
            "Author": "姆麻",
            "ThumImg": "https://twcdn.imtxwy.com/tw/gf/illustration/js/cr065.jpg",
            "LargeImg": "https://twcdn.imtxwy.com/tw/gf/illustration/js/cr064-full.jpg"
        },
        {
            "Id": 65,
            "Title": "沒錯 就是WA醬",
            "Author": "蕭恩",
            "ThumImg": "https://twcdn.imtxwy.com/tw/gf/illustration/js/cr066.jpg",
            "LargeImg": "https://twcdn.imtxwy.com/tw/gf/illustration/js/cr065-full.jpg"
        },
        {
            "Id": 66,
            "Title": "正月",
            "Author": "御麻",
            "ThumImg": "https://twcdn.imtxwy.com/tw/gf/illustration/js/cr067.jpg",
            "LargeImg": "https://twcdn.imtxwy.com/tw/gf/illustration/js/cr066-full.jpg"
        },
        {
            "Id": 67,
            "Title": "與404小隊一起慶祝一周年",
            "Author": "墨亂",
            "ThumImg": "https://twcdn.imtxwy.com/tw/gf/illustration/js/cr068.jpg",
            "LargeImg": "https://twcdn.imtxwy.com/tw/gf/illustration/js/cr067-full.jpg"
        },
        {
            "Id": 68,
            "Title": "散步",
            "Author": "走路常撞牆",
            "ThumImg": "https://twcdn.imtxwy.com/tw/gf/illustration/js/cr069.jpg",
            "LargeImg": "https://twcdn.imtxwy.com/tw/gf/illustration/js/cr068-full.jpg"
        },
        {
            "Id": 69,
            "Title": "賀!繁中少女前線一周年!(順便紅包拿來~",
            "Author": "郁寸",
            "ThumImg": "https://twcdn.imtxwy.com/tw/gf/illustration/js/cr070.jpg",
            "LargeImg": "https://twcdn.imtxwy.com/tw/gf/illustration/js/cr069-full.jpg"
        },
        {
            "Id": 70,
            "Title": "望",
            "Author": "Art Delta",
            "ThumImg": "https://twcdn.imtxwy.com/tw/gf/illustration/js/cr071.jpg",
            "LargeImg": "https://twcdn.imtxwy.com/tw/gf/illustration/js/cr070-full.jpg"
        },
        {
            "Id": 71,
            "Title": "指揮官送你的！？",
            "Author": "蘑菇",
            "ThumImg": "https://twcdn.imtxwy.com/tw/gf/illustration/js/cr072.jpg",
            "LargeImg": "https://twcdn.imtxwy.com/tw/gf/illustration/js/cr071-full.jpg"
        },
        {
            "Id": 72,
            "Title": "RFB的新遊...啊不...是新年快樂啦",
            "Author": "風雨夜Yoru",
            "ThumImg": "https://twcdn.imtxwy.com/tw/gf/illustration/js/cr073.jpg",
            "LargeImg": "https://twcdn.imtxwy.com/tw/gf/illustration/js/cr072-full.jpg"
        },
        {
            "Id": 73,
            "Title": "旺旺來",
            "Author": "袋鼠",
            "ThumImg": "https://twcdn.imtxwy.com/tw/gf/illustration/js/cr074.jpg",
            "LargeImg": "https://twcdn.imtxwy.com/tw/gf/illustration/js/cr073-full.jpg"
        },
        {
            "Id": 74,
            "Title": "下一步",
            "Author": "十一瀰",
            "ThumImg": "https://twcdn.imtxwy.com/tw/gf/illustration/js/cr075.jpg",
            "LargeImg": "https://twcdn.imtxwy.com/tw/gf/illustration/js/cr074-full.jpg"
        },
        {
            "Id": 75,
            "Title": "等待的時間裡",
            "Author": "南瓜浣熊 / 謎狐",
            "ThumImg": "https://twcdn.imtxwy.com/tw/gf/illustration/js/cr076.jpg",
            "LargeImg": "https://twcdn.imtxwy.com/tw/gf/illustration/js/cr075-full.jpg"
        },
        {
            "Id": 76,
            "Title": "休假時去採購的春田太太",
            "Author": "yakanasinhao",
            "ThumImg": "https://twcdn.imtxwy.com/tw/gf/illustration/js/cr077.jpg",
            "LargeImg": "https://twcdn.imtxwy.com/tw/gf/illustration/js/cr076-full.jpg"
        },
        {
            "Id": 77,
            "Title": "AEK的槍被我沒收了",
            "Author": "Nyyyz",
            "ThumImg": "https://twcdn.imtxwy.com/tw/gf/illustration/js/cr078.jpg",
            "LargeImg": "https://twcdn.imtxwy.com/tw/gf/illustration/js/cr077-full.jpg"
        },
        {
            "Id": 78,
            "Title": "HK416 - Ruin Red",
            "Author": "梁爽",
            "ThumImg": "https://twcdn.imtxwy.com/tw/gf/illustration/js/cr079.jpg",
            "LargeImg": "https://twcdn.imtxwy.com/tw/gf/illustration/js/cr078-full.jpg"
        },
        {
            "Id": 79,
            "Title": "G41的誘惑",
            "Author": "Minertime",
            "ThumImg": "https://twcdn.imtxwy.com/tw/gf/illustration/js/cr080.jpg",
            "LargeImg": "https://twcdn.imtxwy.com/tw/gf/illustration/js/cr079-full.jpg"
        },
        {
            "Id": 80,
            "Title": "安全承包公司克魯格和格里芬軍事承包與安全顧問服務中心",
            "Author": "猛達",
            "ThumImg": "https://twcdn.imtxwy.com/tw/gf/illustration/js/cr081.jpg",
            "LargeImg": "https://twcdn.imtxwy.com/tw/gf/illustration/js/cr080-full.jpg"
        },
        {
            "Id": 81,
            "Title": "一周年太太",
            "Author": "Art Lsheng",
            "ThumImg": "https://twcdn.imtxwy.com/tw/gf/illustration/js/cr082.jpg",
            "LargeImg": "https://twcdn.imtxwy.com/tw/gf/illustration/js/cr081-full.jpg"
        },
        {
            "Id": 82,
            "Title": "1st格里芬",
            "Author": "BlackCloud_x",
            "ThumImg": "https://twcdn.imtxwy.com/tw/gf/illustration/js/cr083.jpg",
            "LargeImg": "https://twcdn.imtxwy.com/tw/gf/illustration/js/cr082-full.jpg"
        },
        {
            "Id": 83,
            "Title": "一周年野餐",
            "Author": "亞洛克",
            "ThumImg": "https://twcdn.imtxwy.com/tw/gf/illustration/js/cr084.jpg",
            "LargeImg": "https://twcdn.imtxwy.com/tw/gf/illustration/js/cr083-full.jpg"
        },
        {
            "Id": 84,
            "Title": "404小隊",
            "Author": "禾日",
            "ThumImg": "https://twcdn.imtxwy.com/tw/gf/illustration/js/cr085.jpg",
            "LargeImg": "https://twcdn.imtxwy.com/tw/gf/illustration/js/cr084-full.jpg"
        },
        {
            "Id": 85,
            "Title": "維爾德參上！",
            "Author": "芽",
            "ThumImg": "https://twcdn.imtxwy.com/tw/gf/illustration/js/cr086.jpg",
            "LargeImg": "https://twcdn.imtxwy.com/tw/gf/illustration/js/cr085-full.jpg"
        },
        {
            "Id": 86,
            "Title": "少女前線-T91+T65",
            "Author": "akfox",
            "ThumImg": "https://twcdn.imtxwy.com/tw/gf/illustration/js/cr087.jpg",
            "LargeImg": "https://twcdn.imtxwy.com/tw/gf/illustration/js/cr086-full.jpg"
        }
    ]
}
